README.rst
setup.py
django12factor/__init__.py
django12factor.egg-info/PKG-INFO
django12factor.egg-info/SOURCES.txt
django12factor.egg-info/dependency_links.txt
django12factor.egg-info/pbr.json
django12factor.egg-info/requires.txt
django12factor.egg-info/top_level.txt
django12factor.egg-info/zip-safe