Metadata-Version: 1.1
Name: django12factor
Version: 1.3
Summary: django12factor: Bringing 12factor to Django
Home-page: https://github.com/doismellburning/django12factor
Author: Kristian Glass
Author-email: django12factor@doismellburning.co.uk
License: MIT
Keywords: django 12factor configuration
Platform: UNKNOWN
Classifier: Intended Audience :: Developers
Classifier: License :: OSI Approved :: MIT License
Classifier: Programming Language :: Python :: 2
Classifier: Programming Language :: Python :: 2.7
Classifier: Programming Language :: Python :: 3
Classifier: Programming Language :: Python :: 3.2
Classifier: Programming Language :: Python :: 3.3
Classifier: Programming Language :: Python :: 3.4
